setup.py
basicrpc/__init__.py
basicrpc/basicrpc.py
basicrpc/config.py
basicrpc.egg-info/PKG-INFO
basicrpc.egg-info/SOURCES.txt
basicrpc.egg-info/dependency_links.txt
basicrpc.egg-info/not-zip-safe
basicrpc.egg-info/pbr.json
basicrpc.egg-info/top_level.txt