Metadata-Version: 1.1
Name: basicrpc
Version: 0.0.2
Summary: A very simple Python RPC client
Home-page: https://github.com/muneeb-ali/basicrpc
Author: Jude Nelson and Muneeb Ali
Author-email: support@onename.com
License: MIT
Download-URL: https://github.com/muneeb-ali/basicrpc/archive/master.zip
Keywords: rpc client server netstring
Platform: UNKNOWN
Classifier: Intended Audience :: Developers
Classifier: License :: OSI Approved :: GNU General Public License v3 (GPLv3)
Classifier: Operating System :: OS Independent
Classifier: Programming Language :: Python
Classifier: Topic :: Internet
Classifier: Topic :: Software Development :: Libraries :: Python Modules
